machina/__init__.py
machina/main.py
machina/resources/__init__.py
machina/resources/http_client.py
machina/resources/organization.py
machina/resources/project.py
machina_sdk-1.0.0.dist-info/METADATA
machina_sdk-1.0.0.dist-info/WHEEL
machina_sdk-1.0.0.dist-info/top_level.txt
machina_sdk-1.0.0.dist-info/RECORD
