Metadata-Version: 2.2
Name: machina-sdk
Version: 1.0.0
Summary: Machina Sports API SDK
Author: Fernando Bombassaro Martins
Author-email: Fernando Bombassaro Martins <fernando@machina.gg>
License: MIT
Classifier: Programming Language :: Python :: 3.9
Classifier: License :: OSI Approved :: MIT License
Classifier: Operating System :: OS Independent
Requires-Python: >=3.9,<4.0
Requires-Dist: requests<3.0.0,>=2.26.0
Requires-Dist: pydantic
Dynamic: author
Dynamic: requires-python
